{
  "tenantId":"pb",
  "moduleName":"works",
  "DocumentType":[
    {
      "documentTypeCode":"DT01",
      "name":"BOQ",
      "description":"Defines a document type of BOQ",
      "active":true
    },
    {
      "documentTypeCode":"DT02",
      "name":"Labour Analysis",
      "description":"Defines a document type of Labour Analysis",
      "active":true
    },
    {
      "documentTypeCode":"DT03",
      "name":"Material Analysis",
      "description":"Defines a document type of Material Analysis",
      "active":true
    },
    {
      "documentTypeCode":"DT04",
      "name":"Terms And Conditions",
      "description":"Defines a document type of Terms and conditions",
      "active":true
    },
    {
      "documentTypeCode":"DT05",
      "name":"Others",
      "description":"Defines a document type of Others",
      "active":true
    }
  ]
}
